ThycoticLibrary/__init__.py
robotframework_thycotic-0.0.1.dev1.dist-info/METADATA
robotframework_thycotic-0.0.1.dev1.dist-info/WHEEL
robotframework_thycotic-0.0.1.dev1.dist-info/top_level.txt
robotframework_thycotic-0.0.1.dev1.dist-info/RECORD
