Metadata-Version: 2.1
Name: robotframework-thycotic
Version: 0.0.1.dev1
Summary: RobotFramework Thycotic
Home-page: https://github.com/IlfirinPL/robotframework-thycotic/
Author: Marcin Koperski
Author-email: marcin.koperski+pypi@gmail.com
License: Apache License 2.0
Download-URL: https://github.com/IlfirinPL/robotframework-thycotic/
Keywords: robotframework,thycotic
Platform: UNKNOWN
Requires-Dist: robotframework (>=3.2b1)
Requires-Dist: requests
